economizer/__init__.py
economizer/constants.py
economizer/diagnostics/EconCorrectlyOff.py
economizer/diagnostics/EconCorrectlyOn.py
economizer/diagnostics/ExcessOutsideAir.py
economizer/diagnostics/InsufficientOutsideAir.py
economizer/diagnostics/TemperatureSensor.py
economizer/diagnostics/__init__.py
economizer/economizer_agent.py
volttron_economizer_rcx-2.1.0.dist-info/LICENSE
volttron_economizer_rcx-2.1.0.dist-info/METADATA
volttron_economizer_rcx-2.1.0.dist-info/WHEEL
volttron_economizer_rcx-2.1.0.dist-info/entry_points.txt
volttron_economizer_rcx-2.1.0.dist-info/RECORD
