Metadata-Version: 2.1
Name: volttron-economizer-rcx
Version: 2.1.0
Summary: Economizer Agent helps in the re-tuning process and addresses some of the issues associated with RCx. RCx is known to save energy consumption , but the process used is not cost-effective.  Economizer Agent and it's diagnostics allow continuous re-tuning and problem identification which can lower the costs of RCx
Home-page: https://github.com/eclipse-volttron/volttron-economizer-rcx
License: Apache-2.0
Author: VOLTTRON Team
Author-email: volttron@pnnl.gov
Requires-Python: >=3.10,<4.0
Classifier: Intended Audience :: Developers
Classifier: Intended Audience :: Information Technology
Classifier: Intended Audience :: Other Audience
Classifier: Intended Audience :: Science/Research
Classifier: License :: OSI Approved :: Apache Software License
Classifier: Programming Language :: Python :: 3
Classifier: Programming Language :: Python :: 3.10
Classifier: Programming Language :: Python :: 3.11
Classifier: Programming Language :: Python :: 3 :: Only
Requires-Dist: volttron (>=10.0.2rc0,<11.0)
Project-URL: Repository, https://github.com/eclipse-volttron/volttron-economizer-rcx
